{
  "lookback": 6,
  "best_weight": 0.8,
  "best_threshold": 0.3,
  "dynamic_scale": 70528.80079411954,
  "prophet_regressors": [
    "CPI_Food",
    "AISH_TOTAL",
    "Net_Migration",
    "Mean_Temp"
  ],
  "lgbm_features": [
    "LBS_In_lag1",
    "LBS_In_lag2",
    "LBS_In_lag3",
    "LBS_In_lag4",
    "LBS_In_lag5",
    "LBS_In_lag6",
    "LBS_Out_lag1",
    "LBS_Out_lag2",
    "LBS_Out_lag3",
    "LBS_Out_lag4",
    "LBS_Out_lag5",
    "LBS_Out_lag6",
    "net_lag1",
    "net_lag2",
    "net_lag3",
    "net_lag4",
    "net_lag5",
    "net_lag6",
    "net_3mo_avg",
    "net_6mo_avg",
    "net_3mo_std",
    "net_6mo_std",
    "in_momentum",
    "out_momentum",
    "net_delta",
    "net_acceleration",
    "demand_supply_ratio",
    "deficit_streak",
    "month_sin",
    "month_cos",
    "pressure_index",
    "forecast_uncertainty"
  ]
}